icebox/__init__.py
icebox/box.py
icebox/cli.py
icebox/data.py
icebox/backend/__init__.py
icebox/backend/folder.py
icebox/backend/s3.py
icebox/backend/webdav.py
icebox-1.1.0.dist-info/LICENSE
icebox-1.1.0.dist-info/METADATA
icebox-1.1.0.dist-info/WHEEL
icebox-1.1.0.dist-info/entry_points.txt
icebox-1.1.0.dist-info/top_level.txt
icebox-1.1.0.dist-info/RECORD
