Metadata-Version: 2.1
Name: icebox
Version: 1.1.0
Summary: Encrypting Cold Storage Client
Home-page: https://github.com/alxndr42/icebox
Author: Alexander Dietrich
Author-email: alexander@dietrich.cx
Classifier: Programming Language :: Python :: 3
Classifier: License :: OSI Approved :: GNU General Public License v3 or later (GPLv3+)
Requires-Python: >=3.8
License-File: LICENSE
Requires-Dist: boto3 (~=1.21)
Requires-Dist: click (~=8.0)
Requires-Dist: icepack (~=1.1)
Requires-Dist: pyyaml (~=6.0)
Requires-Dist: retry2 (~=0.9)
Requires-Dist: webdav4 (~=0.9)
